tuneup/__init__.py
tuneup/horserace.py
tuneup/ndimhorserace.py
tuneup/util.py
tuneup-0.0.8.dist-info/METADATA
tuneup-0.0.8.dist-info/WHEEL
tuneup-0.0.8.dist-info/entry_points.txt
tuneup-0.0.8.dist-info/top_level.txt
tuneup-0.0.8.dist-info/RECORD
